__init__.py
kg_gen/__init__.py
kg_gen/cli.py
kg_gen/kg_gen.py
kg_gen/models.py
kg_gen/steps/_1_get_entities.py
kg_gen/steps/_2_get_relations.py
kg_gen/steps/_3_cluster_graph.py
kg_gen/steps/__init__.py
kg_gen/utils/__init__.py
kg_gen/utils/chunk_text.py
kg_gen/utils/template.html
kg_gen/utils/visualize_kg.py
kg_gen-0.4.0.dist-info/METADATA
kg_gen-0.4.0.dist-info/WHEEL
kg_gen-0.4.0.dist-info/entry_points.txt
kg_gen-0.4.0.dist-info/top_level.txt
kg_gen-0.4.0.dist-info/RECORD
