Metadata-Version: 2.4
Name: kg-gen
Version: 0.4.0
Summary: Extract a knowledge graph using LLMs from any text or messages array
Author-email: Belinda Mo <justanexperimentpark@gmail.com>
License-Expression: MIT
Project-URL: Homepage, https://github.com/stair-lab/kg-gen
Project-URL: Issues, https://github.com/stair-lab/kg-gen/issues
Classifier: Programming Language :: Python :: 3
Classifier: Programming Language :: Python :: 3.10
Classifier: Programming Language :: Python :: 3.11
Classifier: Programming Language :: Python :: 3.12
Classifier: Programming Language :: Python :: 3.13
Requires-Python: <4.0,>=3.10
Requires-Dist: nltk
Requires-Dist: pydantic>=2.0.0
Requires-Dist: pre-commit>=4.3.0
Requires-Dist: ty>=0.0.1a21
Requires-Dist: dspy>=2.6.27
Requires-Dist: openai>=1.108.1
Requires-Dist: pyvis>=0.3.2
Requires-Dist: sentence-transformers>=5.1.0
Requires-Dist: tqdm>=4.67.1
Requires-Dist: datasets>=4.1.1
